templated_yaml/__init__.py
templated_yaml/__main__.py
templated_yaml/api.py
templated_yaml/cli.py
templated_yaml/context.py
templated_yaml/flatten.py
templated_yaml/meta.py
templated_yaml/resolver.py
templated_yaml/settings.py
templated_yaml-2.0.0.dist-info/METADATA
templated_yaml-2.0.0.dist-info/WHEEL
templated_yaml-2.0.0.dist-info/entry_points.txt
templated_yaml-2.0.0.dist-info/top_level.txt
templated_yaml-2.0.0.dist-info/RECORD
